listpicker/__init__.py
listpicker/keyboard.py
listpicker/listpicker.py
listpicker/py.typed
listpicker/util.py
listpicker-0.3.3.dist-info/METADATA
listpicker-0.3.3.dist-info/WHEEL
listpicker-0.3.3.dist-info/licenses/LICENSE
listpicker-0.3.3.dist-info/RECORD
