Metadata-Version: 2.4
Name: listpicker
Version: 0.3.3
Summary: Interactive list selection and multiselect for POSIX terminals (non-curses)
Project-URL: Homepage, https://github.com/guns/python-listpicker
Project-URL: Repository, https://github.com/guns/python-listpicker.git
Author-email: Sung Pae <self@sungpae.com>
License: The MIT License (MIT)
License-File: LICENSE
Keywords: list selection,multiple select,multiselect
Classifier: Development Status :: 3 - Alpha
Classifier: Intended Audience :: Developers
Classifier: License :: OSI Approved :: MIT License
Classifier: Operating System :: POSIX
Classifier: Programming Language :: Python :: 3.10
Classifier: Topic :: Software Development :: Libraries :: Python Modules
Classifier: Topic :: Software Development :: User Interfaces
Classifier: Topic :: Terminals
Requires-Python: >=3.10
Requires-Dist: regex
Provides-Extra: dev
Requires-Dist: types-regex; extra == 'dev'
